{"name": "Newcomb", "region_id": "region_100", "lat": 38.0357625021372, "station_id": "hub_449", "channel": "US-Bike-Sharing-Channel", "num_bikes_available": 6, "country_code": "US", "last_reported": 1495379620, "is_returning": 1, "rental_methods": ["KEY", "APPLEPAY", "ANDROIDPAY", "TRANSITCARD", "ACCOUNTNUMBER", "PHONE"], "is_installed": 1, "lon": -78.5072994363201, "num_bikes_disabled": 0, "is_renting": 1, "address": "194 Newcomb Road South, Brown College at Monroe Hill, Charlottesville", "num_docks_available": 4, "publisher": "ubike.virginia.edu"}
{"name": "Monroe", "region_id": "region_100", "lat": 38.0344845637197, "station_id": "hub_457", "channel": "US-Bike-Sharing-Channel", "num_bikes_available": 4, "country_code": "US", "last_reported": 1495379620, "is_returning": 1, "rental_methods": ["KEY", "APPLEPAY", "ANDROIDPAY", "TRANSITCARD", "ACCOUNTNUMBER", "PHONE"], "is_installed": 1, "lon": -78.5062674316095, "num_bikes_disabled": 0, "is_renting": 1, "address": "James Monroe Hall, McCormick Road, Carr's Hill, Virginia", "num_docks_available": 6, "publisher": "ubike.virginia.edu"}
{"name": "Arts", "region_id": "region_100", "lat": 38.0390685493136, "station_id": "hub_458", "channel": "US-Bike-Sharing-Channel", "num_bikes_available": 11, "country_code": "US", "last_reported": 1495379620, "is_returning": 1, "rental_methods": ["KEY", "APPLEPAY", "ANDROIDPAY", "TRANSITCARD", "ACCOUNTNUMBER", "PHONE"], "is_installed": 1, "lon": -78.5030481832028, "num_bikes_disabled": 0, "is_renting": 1, "address": "Fiske Kimball Fine Arts Library, Bayly Drive, Carr's Hill, Virginia", "num_docks_available": 7, "publisher": "ubike.virginia.edu"}
{"name": "The Corner", "region_id": "region_100", "lat": 38.0343730752369, "station_id": "hub_459", "channel": "US-Bike-Sharing-Channel", "num_bikes_available": 3, "country_code": "US", "last_reported": 1495379620, "is_returning": 1, "rental_methods": ["KEY", "APPLEPAY", "ANDROIDPAY", "TRANSITCARD", "ACCOUNTNUMBER", "PHONE"], "is_installed": 1, "lon": -78.5006812398122, "num_bikes_disabled": 0, "is_renting": 1, "address": "USPS, Hospital Drive, Carr's Hill, Virginia", "num_docks_available": 6, "publisher": "ubike.virginia.edu"}
{"name": "West Main", "region_id": "region_100", "lat": 38.0329898598805, "station_id": "hub_460", "channel": "US-Bike-Sharing-Channel", "num_bikes_available": 0, "country_code": "US", "last_reported": 1495379620, "is_returning": 1, "rental_methods": ["KEY", "APPLEPAY", "ANDROIDPAY", "TRANSITCARD", "ACCOUNTNUMBER", "PHONE"], "is_installed": 1, "lon": -78.4962426976086, "num_bikes_disabled": 0, "is_renting": 1, "address": "Bikeshare, West Main Street, Vinegar Hill, Charlottesville, Virginia", "num_docks_available": 10, "publisher": "ubike.virginia.edu"}
{"name": "JPA ", "region_id": "region_100", "lat": 38.0325450673676, "station_id": "hub_461", "channel": "US-Bike-Sharing-Channel", "num_bikes_available": 7, "country_code": "US", "last_reported": 1495379620, "is_returning": 1, "rental_methods": ["KEY", "APPLEPAY", "ANDROIDPAY", "TRANSITCARD", "ACCOUNTNUMBER", "PHONE"], "is_installed": 1, "lon": -78.5003006307518, "num_bikes_disabled": 0, "is_renting": 1, "address": "1340 Jefferson Park Avenue, University of Virginia, Charlottesville", "num_docks_available": 5, "publisher": "ubike.virginia.edu"}
{"name": "McLeod", "region_id": "region_100", "lat": 38.0312797969963, "station_id": "hub_463", "channel": "US-Bike-Sharing-Channel", "num_bikes_available": 6, "country_code": "US", "last_reported": 1495379620, "is_returning": 1, "rental_methods": ["KEY", "APPLEPAY", "ANDROIDPAY", "TRANSITCARD", "ACCOUNTNUMBER", "PHONE"], "is_installed": 1, "lon": -78.5018033762398, "num_bikes_disabled": 0, "is_renting": 1, "address": "204-208 Jeanette Lancaster Way, University of Virginia, Charlottesville", "num_docks_available": 5, "publisher": "ubike.virginia.edu"}
{"name": "Bryan", "region_id": "region_100", "lat": 38.0331279040488, "station_id": "hub_465", "channel": "US-Bike-Sharing-Channel", "num_bikes_available": 3, "country_code": "US", "last_reported": 1495379620, "is_returning": 1, "rental_methods": ["KEY", "APPLEPAY", "ANDROIDPAY", "TRANSITCARD", "ACCOUNTNUMBER", "PHONE"], "is_installed": 1, "lon": -78.5059109153744, "num_bikes_disabled": 0, "is_renting": 1, "address": "John Stewart Bryan Hall, Cabell Drive, McCormick Road Houses, Virginia", "num_docks_available": 4, "publisher": "ubike.virginia.edu"}
{"name": "Minor", "region_id": "region_100", "lat": 38.0336914824361, "station_id": "hub_466", "channel": "US-Bike-Sharing-Channel", "num_bikes_available": 6, "country_code": "US", "last_reported": 1495379620, "is_returning": 1, "rental_methods": ["KEY", "APPLEPAY", "ANDROIDPAY", "TRANSITCARD", "ACCOUNTNUMBER", "PHONE"], "is_installed": 1, "lon": -78.5063430062728, "num_bikes_disabled": 0, "is_renting": 1, "address": "Bike Rack, Cabell Drive, McCormick Road Houses, Virginia", "num_docks_available": 3, "publisher": "ubike.virginia.edu"}
{"name": "Clark", "region_id": "region_100", "lat": 38.0337250457061, "station_id": "hub_467", "channel": "US-Bike-Sharing-Channel", "num_bikes_available": 8, "country_code": "US", "last_reported": 1495379620, "is_returning": 1, "rental_methods": ["KEY", "APPLEPAY", "ANDROIDPAY", "TRANSITCARD", "ACCOUNTNUMBER", "PHONE"], "is_installed": 1, "lon": -78.5073372056738, "num_bikes_disabled": 0, "is_renting": 1, "address": "UTS Stop, McCormick Road, Carr's Hill, Virginia", "num_docks_available": 9, "publisher": "ubike.virginia.edu"}
